CHANGES
LICENSE
MANIFEST.in
README.rst
setup.cfg
setup.py
amazonproduct/__init__.py
amazonproduct/api.py
amazonproduct/errors.py
amazonproduct/utils.py
amazonproduct/version.py
amazonproduct/contrib/__init__.py
amazonproduct/contrib/caching.py
amazonproduct/contrib/cart.py
amazonproduct/contrib/retry.py
amazonproduct/processors/__init__.py
amazonproduct/processors/_lxml.py
amazonproduct/processors/elementtree.py
amazonproduct/processors/etree.py
amazonproduct/processors/minidom.py
amazonproduct/processors/objectify.py
python_amazon_product_api.egg-info/PKG-INFO
python_amazon_product_api.egg-info/SOURCES.txt
python_amazon_product_api.egg-info/dependency_links.txt
python_amazon_product_api.egg-info/not-zip-safe
python_amazon_product_api.egg-info/top_level.txt
tests/APICalls-fails-for-too-many-requests.xml
tests/APICalls-fails-for-wrong-aws-key.xml
tests/__init__.py
tests/conftest.py
tests/internal-error.xml
tests/parser-performance.py
tests/runtests.py
tests/test_api_basics.py
tests/test_contrib_retry.py
tests/test_utils.py
tests/test_xml_responses.py
tests/utils.py
tests/2011-08-01/APICredentials-ca-without-credentials-fails.xml
tests/2011-08-01/APICredentials-de-without-credentials-fails.xml
tests/2011-08-01/APICredentials-es-without-credentials-fails.xml
tests/2011-08-01/APICredentials-fr-without-credentials-fails.xml
tests/2011-08-01/APICredentials-it-without-credentials-fails.xml
tests/2011-08-01/APICredentials-jp-without-credentials-fails.xml
tests/2011-08-01/APICredentials-uk-without-credentials-fails.xml
tests/2011-08-01/APICredentials-us-without-credentials-fails.xml
tests/2011-08-01/BrowseNodeLookup-ca-books-browsenode.xml
tests/2011-08-01/BrowseNodeLookup-ca-fails-for-wrong-input-2.xml
tests/2011-08-01/BrowseNodeLookup-ca-fails-for-wrong-input.xml
tests/2011-08-01/BrowseNodeLookup-cn-books-browsenode.xml
tests/2011-08-01/BrowseNodeLookup-cn-fails-for-wrong-input-2.xml
tests/2011-08-01/BrowseNodeLookup-cn-fails-for-wrong-input.xml
tests/2011-08-01/BrowseNodeLookup-de-books-browsenode.xml
tests/2011-08-01/BrowseNodeLookup-de-fails-for-wrong-input-2.xml
tests/2011-08-01/BrowseNodeLookup-de-fails-for-wrong-input.xml
tests/2011-08-01/BrowseNodeLookup-es-books-browsenode.xml
