Metadata-Version: 1.1
Name: python-amazon-product-api
Version: 0.2.7
Summary: A Python wrapper for the Amazon Product Advertising API.
Home-page: http://bitbucket.org/basti/python-amazon-product-api/downloads/
Author: Sebastian Rahlf
Author-email: basti AT redtoad DOT de
License: bsd
Keywords: amazon product advertising api wrapper signed requests
Platform: UNKNOWN
Classifier: Operating System :: OS Independent
Classifier: Development Status :: 4 - Beta
Classifier: Intended Audience :: Developers
Classifier: License :: OSI Approved :: BSD License
Classifier: Operating System :: OS Independent
Classifier: Programming Language :: Python :: 2.4
Classifier: Programming Language :: Python :: 2.5
Classifier: Programming Language :: Python :: 2.6
Classifier: Programming Language :: Python :: 2.7
Classifier: Topic :: Internet :: WWW/HTTP
Classifier: Topic :: Software Development :: Libraries :: Python Modules
